capgenie/__init__.py
capgenie/file_manager.py
capgenie/project_editor.py
capgenie-0.1.0.dist-info/METADATA
capgenie-0.1.0.dist-info/WHEEL
capgenie-0.1.0.dist-info/licenses/LICENSE
capgenie-0.1.0.dist-info/RECORD
