Metadata-Version: 2.4
Name: capgenie
Version: 0.1.0
Summary: A Python tool to programmatically edit CapCut project files via JSON manipulation.
Project-URL: Homepage, https://github.com/YanisDjeroro/CapGenie
Project-URL: Repository, https://github.com/YanisDjeroro/CapGenie
Project-URL: Bug Reports, https://github.com/YanisDjeroro/CapGenie/issues
Author: Yanis
License: MIT
License-File: LICENSE
Keywords: ai,automation,capcut,json,video editing
Classifier: Development Status :: 3 - Alpha
Classifier: Intended Audience :: Developers
Classifier: License :: OSI Approved :: MIT License
Classifier: Programming Language :: Python :: 3
Classifier: Programming Language :: Python :: 3.8
Classifier: Programming Language :: Python :: 3.9
Classifier: Programming Language :: Python :: 3.10
Classifier: Programming Language :: Python :: 3.11
Classifier: Programming Language :: Python :: 3.12
Classifier: Topic :: Multimedia :: Video
Classifier: Topic :: Software Development :: Libraries :: Python Modules
Requires-Python: >=3.8
Provides-Extra: dev
Requires-Dist: black>=23.0; extra == 'dev'
Requires-Dist: build>=0.10; extra == 'dev'
Requires-Dist: isort>=5.0; extra == 'dev'
Requires-Dist: pytest-cov>=4.0; extra == 'dev'
Requires-Dist: pytest>=7.0; extra == 'dev'
Requires-Dist: twine>=3.0; extra == 'dev'
